{
  "dataset_rows": 207,
  "class_balance": 0.7584541062801933,
  "winner": {
    "split_mode": "rolling_5y",
    "model_name": "hgb",
    "selection_policy": "top_30pct",
    "sample_count": 35,
    "years_covered": 6,
    "events_per_year": 5.833333333333333,
    "win_rate": 0.9142857142857143,
    "avg_return": 0.03698563052065987,
    "median_return": 0.03413376281982572,
    "avg_max_drawdown": -0.01915666367251596,
    "avg_max_runup": 0.050762905677994775,
    "positive_year_ratio": 1.0
  },
  "top_strategies": [
    {
      "split_mode": "rolling_5y",
      "model_name": "hgb",
      "selection_policy": "top_30pct",
      "sample_count": 35,
      "years_covered": 6,
      "events_per_year": 5.833333333333333,
      "win_rate": 0.9142857142857143,
      "avg_return": 0.03698563052065987,
      "median_return": 0.03413376281982572,
      "avg_max_drawdown": -0.01915666367251596,
      "avg_max_runup": 0.050762905677994775,
      "positive_year_ratio": 1.0
    },
    {
      "split_mode": "rolling_5y",
      "model_name": "xgb",
      "selection_policy": "top_30pct",
      "sample_count": 35,
      "years_covered": 6,
      "events_per_year": 5.833333333333333,
      "win_rate": 0.8285714285714286,
      "avg_return": 0.034159027489375826,
      "median_return": 0.031670134301981845,
      "avg_max_drawdown": -0.0169336981472197,
      "avg_max_runup": 0.04785212674061059,
      "positive_year_ratio": 1.0
    },
    {
      "split_mode": "rolling_5y",
      "model_name": "hgb",
      "selection_policy": "top_50pct",
      "sample_count": 58,
      "years_covered": 6,
      "events_per_year": 9.666666666666666,
      "win_rate": 0.8620689655172413,
      "avg_return": 0.03123009947352202,
      "median_return": 0.027574844999636028,
      "avg_max_drawdown": -0.0216107008294248,
      "avg_max_runup": 0.04809830898984896,
      "positive_year_ratio": 1.0
    },
    {
      "split_mode": "expanding",
      "model_name": "xgb",
      "selection_policy": "top_30pct",
      "sample_count": 35,
      "years_covered": 6,
      "events_per_year": 5.833333333333333,
      "win_rate": 0.7428571428571429,
      "avg_return": 0.029004226414301764,
      "median_return": 0.027801084471643422,
      "avg_max_drawdown": -0.01903870320281381,
      "avg_max_runup": 0.04861613983558543,
      "positive_year_ratio": 1.0
    },
    {
      "split_mode": "expanding",
      "model_name": "hgb",
      "selection_policy": "top_30pct",
      "sample_count": 35,
      "years_covered": 6,
      "events_per_year": 5.833333333333333,
      "win_rate": 0.7714285714285715,
      "avg_return": 0.028934817534335775,
      "median_return": 0.03136334015876008,
      "avg_max_drawdown": -0.01962438976683275,
      "avg_max_runup": 0.04771382030208706,
      "positive_year_ratio": 0.8333333333333334
    },
    {
      "split_mode": "rolling_5y",
      "model_name": "rf",
      "selection_policy": "top_30pct",
      "sample_count": 35,
      "years_covered": 6,
      "events_per_year": 5.833333333333333,
      "win_rate": 0.7714285714285715,
      "avg_return": 0.02867903965913302,
      "median_return": 0.02586544034280225,
      "avg_max_drawdown": -0.01965905651906064,
      "avg_max_runup": 0.04748371177610781,
      "positive_year_ratio": 1.0
    },
    {
      "split_mode": "rolling_5y",
      "model_name": "xgb",
      "selection_policy": "top_50pct",
      "sample_count": 58,
      "years_covered": 6,
      "events_per_year": 9.666666666666666,
      "win_rate": 0.7758620689655172,
      "avg_return": 0.027504571880845388,
      "median_return": 0.025323587956236238,
      "avg_max_drawdown": -0.02065211659454252,
      "avg_max_runup": 0.044576816783656575,
      "positive_year_ratio": 1.0
    },
    {
      "split_mode": "expanding",
      "model_name": "hgb",
      "selection_policy": "top_50pct",
      "sample_count": 58,
      "years_covered": 6,
      "events_per_year": 9.666666666666666,
      "win_rate": 0.8103448275862069,
      "avg_return": 0.027263124336221155,
      "median_return": 0.025323587956236238,
      "avg_max_drawdown": -0.01967785910746088,
      "avg_max_runup": 0.04373402517007518,
      "positive_year_ratio": 1.0
    },
    {
      "split_mode": "rolling_5y",
      "model_name": "rf",
      "selection_policy": "top_50pct",
      "sample_count": 58,
      "years_covered": 6,
      "events_per_year": 9.666666666666666,
      "win_rate": 0.7758620689655172,
      "avg_return": 0.02671707591476175,
      "median_return": 0.024921538035733826,
      "avg_max_drawdown": -0.02154444976014948,
      "avg_max_runup": 0.04524657345286291,
      "positive_year_ratio": 1.0
    },
    {
      "split_mode": "expanding",
      "model_name": "xgb",
      "selection_policy": "top_50pct",
      "sample_count": 58,
      "years_covered": 6,
      "events_per_year": 9.666666666666666,
      "win_rate": 0.7241379310344828,
      "avg_return": 0.02533815282339064,
      "median_return": 0.02190575488723323,
      "avg_max_drawdown": -0.019547886283281884,
      "avg_max_runup": 0.04561501118031849,
      "positive_year_ratio": 1.0
    },
    {
      "split_mode": "expanding",
      "model_name": "rule_baseline",
      "selection_policy": "all",
      "sample_count": 113,
      "years_covered": 6,
      "events_per_year": 18.833333333333332,
      "win_rate": 0.7433628318584071,
      "avg_return": 0.02304689687386328,
      "median_return": 0.020504276935833454,
      "avg_max_drawdown": -0.022984561849837347,
      "avg_max_runup": 0.042772118939123825,
      "positive_year_ratio": 1.0
    },
    {
      "split_mode": "rolling_5y",
      "model_name": "rule_baseline",
      "selection_policy": "all",
      "sample_count": 113,
      "years_covered": 6,
      "events_per_year": 18.833333333333332,
      "win_rate": 0.7433628318584071,
      "avg_return": 0.02304689687386328,
      "median_return": 0.020504276935833454,
      "avg_max_drawdown": -0.022984561849837347,
      "avg_max_runup": 0.042772118939123825,
      "positive_year_ratio": 1.0
    }
  ]
}